BI_microdata_extractor/BI_microdata_extractor.py
BI_microdata_extractor/__init__.py
BI_microdata_extractor-0.0.1.dist-info/LICENSE
BI_microdata_extractor-0.0.1.dist-info/METADATA
BI_microdata_extractor-0.0.1.dist-info/WHEEL
BI_microdata_extractor-0.0.1.dist-info/top_level.txt
BI_microdata_extractor-0.0.1.dist-info/RECORD
