Metadata-Version: 2.1
Name: BI-microdata-extractor
Version: 0.0.1
Summary: A tool for navigating and processing the microdata od Banca d'Italia: Indagine sul Bilancio dell Famiglie Italiane
Home-page: https://github.com/Clearbox-AI/bancaitalia-microdata-extractor
Author: Dario Brunelli
Author-email: Clearbox AI <info@clearbox.ai>
Project-URL: Homepage, https://github.com/Clearbox-AI/BI-microdata-extractor
Requires-Python: >3.9
License-File: LICENSE
Requires-Dist: polars==1.17.1
Requires-Dist: pandas<3.0
Provides-Extra: dev
Requires-Dist: check-manifest; extra == "dev"
Requires-Dist: pytest>3.9; extra == "dev"
Provides-Extra: test
Requires-Dist: coverage; extra == "test"
